fugue_ml/__init__.py
fugue_ml/utils/__init__.py
fugue_ml/utils/numpy.py
fugue_ml_version/__init__.py
tests/__init__.py
tests/utils/__init__.py
tests/utils/test_numpy.py
fugue_ml-0.0.2.dist-info/LICENSE
fugue_ml-0.0.2.dist-info/METADATA
fugue_ml-0.0.2.dist-info/WHEEL
fugue_ml-0.0.2.dist-info/entry_points.txt
fugue_ml-0.0.2.dist-info/top_level.txt
fugue_ml-0.0.2.dist-info/RECORD
